cpyprocess.cpython-310-darwin.so
cpyprocess-0.0.1.dist-info/METADATA
cpyprocess-0.0.1.dist-info/WHEEL
cpyprocess-0.0.1.dist-info/top_level.txt
cpyprocess-0.0.1.dist-info/RECORD
