Metadata-Version: 2.1
Name: cpyprocess
Version: 0.0.1
Summary: A simple Python wrapper for popen() in C++
Author: Aahan Patel
Author-email: aahanp@gmail.com
Requires-Python: >=3.7
Provides-Extra: test
Requires-Dist: pytest (>=6.0) ; extra == 'test'
